.gitignore
LICENSE
README.rst
odictliteral.py
setup.py
odictliteral.egg-info/PKG-INFO
odictliteral.egg-info/SOURCES.txt
odictliteral.egg-info/dependency_links.txt
odictliteral.egg-info/top_level.txt