Metadata-Version: 1.1
Name: odictliteral
Version: 1.0.0
Summary: A tidier way of coding literal OrderedDicts
Home-page: https://github.com/ajtowns/odictliteral
Author: Anthony Towns
Author-email: aj@erisian.com.au
License: MIT
Platform: UNKNOWN
Classifier: Development Status :: 4 - Beta
Classifier: Intended Audience :: Developers
Classifier: Programming Language :: Python :: 2
Classifier: Programming Language :: Python :: 3
